trackle/__init__.py
trackle/cli.py
trackle/cli_note.py
trackle/cli_todo.py
trackle/note_shell.py
trackle/shell.py
trackle/todo_shell.py
trackle/core/__init__.py
trackle/core/note.py
trackle/core/storage.py
trackle/core/todo.py
trackle/tests/__init__.py
trackle/tests/test_cli.py
trackle/tests/test_note.py
trackle/tests/test_shell.py
trackle/tests/test_storage.py
trackle/tests/test_todo.py
trackle/utils/__init__.py
trackle/utils/editor.py
trackle-0.1.3.dist-info/METADATA
trackle-0.1.3.dist-info/WHEEL
trackle-0.1.3.dist-info/entry_points.txt
trackle-0.1.3.dist-info/top_level.txt
trackle-0.1.3.dist-info/RECORD
