Metadata-Version: 2.4
Name: trackle
Version: 0.1.3
Requires-Dist: sentence-transformers
Requires-Dist: faiss-cpu
Requires-Dist: typer
Requires-Dist: pyyaml
Requires-Dist: prompt_toolkit
Requires-Dist: python-dateutil
Dynamic: requires-dist
